infp/BigNumber.py
infp/__init__.py
infp-0.0.3.dist-info/METADATA
infp-0.0.3.dist-info/WHEEL
infp-0.0.3.dist-info/top_level.txt
infp-0.0.3.dist-info/RECORD
