Metadata-Version: 2.1
Name: infp
Version: 0.0.3
Summary: Add, Multiply, Mod, Divide Large number
Author: Vu Diep
Author-email: vudiep411@gmail.com
Keywords: python,data structure,math,big number,infinite precision
